studip_cli/browser.py
studip_cli/main.py
studip_cli-0.1.0.dist-info/METADATA
studip_cli-0.1.0.dist-info/WHEEL
studip_cli-0.1.0.dist-info/entry_points.txt
studip_cli-0.1.0.dist-info/RECORD
