Metadata-Version: 2.1
Name: studip-cli
Version: 0.1.0
Summary: Studip cli tool
Author: FrederikRichter
Author-email: Frederik.Richter@mailbox.org
Requires-Python: >=3.11,<4.0
Classifier: Programming Language :: Python :: 3
Classifier: Programming Language :: Python :: 3.11
Classifier: Programming Language :: Python :: 3.12
Requires-Dist: lxml (>=5.1.0,<6.0.0)
Requires-Dist: python-dotenv (>=1.0.0,<2.0.0)
Requires-Dist: requests (>=2.31.0,<3.0.0)
Requires-Dist: temp (>=2020.7.2,<2021.0.0)
